soyuz/__init__.py
soyuz/configuration.py
soyuz/entrypoint.py
soyuz/utils.py
soyuz/data/__init__.py
soyuz/data/daemons.py
soyuz/data/files.py
soyuz/data/folders.py
soyuz/dx/__init__.py
soyuz/dx/context.py
soyuz/dx/sentinels.py
soyuz/dx/uploaders.py
soyuz/dx/variables.py
natera_dnanexus_uploader-1.0.0.dist-info/LICENSE.txt
natera_dnanexus_uploader-1.0.0.dist-info/METADATA
natera_dnanexus_uploader-1.0.0.dist-info/WHEEL
natera_dnanexus_uploader-1.0.0.dist-info/entry_points.txt
natera_dnanexus_uploader-1.0.0.dist-info/top_level.txt
natera_dnanexus_uploader-1.0.0.dist-info/RECORD
