Metadata-Version: 2.1
Name: natera-dnanexus-uploader
Version: 1.0.0
Summary: Natera Uploader
Home-page: UNKNOWN
Author: Nikita Berezin
Author-email: nberezin@natera.com
License: UNKNOWN
Platform: UNKNOWN
Classifier: Programming Language :: Python :: 2
Requires-Python: >=2.7
Requires-Dist: dxpy (>=0.288.0)
